lhub/__init__.py
lhub/api.py
lhub/lhub.py
lhub/log.py
lhub/url.py
lhub/common/__init__.py
lhub/common/decorators.py
lhub/common/dicts_and_lists.py
lhub/common/helpers.py
lhub/common/time.py
lhub/common/url.py
lhub/exceptions/__init__.py
lhub/exceptions/app.py
lhub/exceptions/auth.py
lhub/exceptions/base.py
lhub/exceptions/formatting.py
lhub/exceptions/validation.py
lhub-0.2.6.2.dist-info/LICENSE
lhub-0.2.6.2.dist-info/METADATA
lhub-0.2.6.2.dist-info/WHEEL
lhub-0.2.6.2.dist-info/top_level.txt
lhub-0.2.6.2.dist-info/RECORD
