Metadata-Version: 2.1
Name: lhub
Version: 0.2.6.2
Summary: LogicHub API Wrapper
Home-page: https://github.com/deathbywedgie/lhub
Author: Chad Roberts
Author-email: chad@logichub.com
License: UNKNOWN
Project-URL: Bug Tracker, https://github.com/deathbywedgie/lhub/issues
Keywords: python,lhub,LogicHub,api,security
Platform: UNKNOWN
Classifier: Development Status :: 3 - Alpha
Classifier: Intended Audience :: Developers
Classifier: Intended Audience :: System Administrators
Classifier: Intended Audience :: Information Technology
Classifier: Programming Language :: Python :: 3
Classifier: Programming Language :: Python :: 3.7
Classifier: Natural Language :: English
License-File: LICENSE
Requires-Dist: requests
Requires-Dist: multipledispatch
